daterangefilter/__init__.py
daterangefilter/apps.py
daterangefilter/filters.py
daterangefilter/models.py
daterangefilter/tests.py
daterangefilter/locale/ru/LC_MESSAGES/django.mo
daterangefilter/locale/ru/LC_MESSAGES/django.po
daterangefilter/static/daterangefilter/daterangepicker/daterangepicker.css
daterangefilter/static/daterangefilter/daterangepicker/daterangepicker.min.js
daterangefilter/static/daterangefilter/moment/moment-with-locales.min.js
daterangefilter/static/daterangefilter/moment/moment.min.js
daterangefilter/static/daterangefilter/moment/locale/ru.js
daterangefilter/templates/daterangefilter/_future_ranges.html
daterangefilter/templates/daterangefilter/_load_momentjs.html
daterangefilter/templates/daterangefilter/_past_ranges.html
daterangefilter/templates/daterangefilter/daterangefilter.html
daterangefilter/templates/daterangefilter/ranges.html
daterangefilter/templates/daterangefilter/suit_daterangefilter.html
dj_daterangefilter-0.1.2.dist-info/LICENSE
dj_daterangefilter-0.1.2.dist-info/METADATA
dj_daterangefilter-0.1.2.dist-info/WHEEL
dj_daterangefilter-0.1.2.dist-info/top_level.txt
dj_daterangefilter-0.1.2.dist-info/RECORD
