Metadata-Version: 2.1
Name: dj-daterangefilter
Version: 0.1.2
Summary: Date range filter for Django admin
Home-page: https://github.com/mahfouzalsheikh/dj-daterangefilter/tree/master
Author: Andrey Novikov
Author-email: novikov@gmail.com
License: MIT
Project-URL: Source, https://github.com/mahfouzalsheikh/dj-daterangefilter/
Project-URL: Tracker, https://github.com/mahfouzalsheikh/dj-daterangefilter/issues
Platform: UNKNOWN
Classifier: Development Status :: 5 - Production/Stable
Classifier: Framework :: Django
Classifier: Programming Language :: Python
Classifier: Programming Language :: Python :: 2
Classifier: Programming Language :: Python :: 3
Classifier: License :: OSI Approved :: MIT License
Classifier: Operating System :: OS Independent
License-File: LICENSE
